LICENCE.md
README.md
setup.py
Topsis_apoorva_101903432.egg-info/PKG-INFO
Topsis_apoorva_101903432.egg-info/SOURCES.txt
Topsis_apoorva_101903432.egg-info/dependency_links.txt
Topsis_apoorva_101903432.egg-info/top_level.txt
apoorva/__init__.py
apoorva/topsis.py